{
  "manufacturer": "3DHoJor",
  "filaments": [
    {
      "name": "Basic PLA {color_name}",
      "material": "PLA",
      "density": 1.24,
      "weights": [
        {
          "weight": 1000,
          "spool_type": "plastic"
        }
      ],
      "diameters": [
        1.75
      ],
      "extruder_temp_range": [
        190,
        220
      ],
      "bed_temp_range": [
        50,
        60
      ],
      "country_of_origin": "China",
      "colors": [
        {
          "name": "Basic Black",
          "codes": [
            "HJ-Hyper PLA-175B1-DE",
            "HJ-Hyper PLA-175B1-US"
          ],
          "hex": "1a1a1a"
        },
        {
          "name": "Basic Blue",
          "codes": [
            "HJ-Hyper PLA-175U1-DE",
            "HJ-Hyper PLA-175U1-US"
          ],
          "hex": "1e3a8a"
        },
        {
          "name": "Basic Cold White",
          "codes": [
            "HJ-Hyper PLA-175CW1-DE",
            "HJ-Hyper PLA-175CW1-US"
          ],
          "hex": "f0f4f8"
        },
        {
          "name": "Basic Fire Engine Red",
          "codes": [
            "HJ-Hyper PLA-175FR1-DE",
            "HJ-Hyper PLA-175FR1-US"
          ],
          "hex": "ce2029"
        },
        {
          "name": "Basic Green",
          "codes": [
            "HJ-Hyper PLA-175G1-DE",
            "HJ-Hyper PLA-175G1-US"
          ],
          "hex": "2e7d32"
        },
        {
          "name": "Basic Grey",
          "codes": [
            "HJ-Hyper PLA-175H1-DE",
            "HJ-Hyper PLA-175H1-US"
          ],
          "hex": "808080"
        },
        {
          "name": "Basic Light Blue",
          "codes": [
            "HJ-Hyper PLA-175LU1-DE",
            "HJ-Hyper PLA-175LU1-US"
          ],
          "hex": "87ceeb"
        },
        {
          "name": "Basic Light Gray",
          "codes": [
            "HJ-Hyper PLA-175LH1-DE",
            "HJ-Hyper PLA-175LH1-US"
          ],
          "hex": "b0b0b0"
        },
        {
          "name": "Basic Orange",
          "codes": [
            "HJ-Hyper PLA-175O1-DE",
            "HJ-Hyper PLA-175O1-US"
          ],
          "hex": "ff8c00"
        },
        {
          "name": "Basic Pink",
          "codes": [
            "HJ-Hyper PLA-175P1-DE",
            "HJ-Hyper PLA-175P1-US"
          ],
          "hex": "ff69b4"
        },
        {
          "name": "Basic Purple",
          "codes": [
            "HJ-Hyper PLA-175Z1-DE",
            "HJ-Hyper PLA-175Z1-US"
          ],
          "hex": "800080"
        },
        {
          "name": "Basic Silver",
          "codes": [
            "HJ-Hyper PLA-175S1-DE",
            "HJ-Hyper PLA-175S1-US"
          ],
          "hex": "c0c0c0"
        },
        {
          "name": "Basic White",
          "codes": [
            "HJ-Hyper PLA-175W1-DE",
            "HJ-Hyper PLA-175W1-US"
          ],
          "hex": "f5f5f5"
        }
      ]
    },
    {
      "name": "Crystal Rainbow PLA {color_name}",
      "material": "PLA",
      "density": 1.24,
      "weights": [
        {
          "weight": 1000,
          "spool_type": "plastic"
        }
      ],
      "diameters": [
        1.75
      ],
      "extruder_temp_range": [
        190,
        220
      ],
      "bed_temp_range": [
        50,
        60
      ],
      "country_of_origin": "China",
      "colors": [
        {
          "name": "Crystal Rainbow Flame",
          "codes": [
            "HJ-PLA-CrystalRainbow-175FL1-US"
          ],
          "hexes": [
            "ff4500",
            "ff6b35",
            "ffd700",
            "ff8c00"
          ],
          "multi_color_direction": "longitudinal"
        },
        {
          "name": "Crystal Rainbow Galaxy",
          "codes": [
            "HJ-PLA-CrystalRainbow-175GA1-US"
          ],
          "hexes": [
            "1a1a2e",
            "4a148c",
            "1565c0",
            "ffd700"
          ],
          "multi_color_direction": "longitudinal"
        },
        {
          "name": "Crystal Rainbow Glacier",
          "codes": [
            "HJ-PLA-CrystalRainbow-175TBW1-US"
          ],
          "hexes": [
            "a8d8ea",
            "81d4fa",
            "b3e5fc",
            "e1f5fe"
          ],
          "multi_color_direction": "longitudinal"
        },
        {
          "name": "Crystal Rainbow Late Autumn",
          "codes": [
            "HJ-PLA-CrystalRainbow-175LA1-US"
          ],
          "hexes": [
            "d35400",
            "e67e22",
            "f1c40f",
            "8b4513"
          ],
          "multi_color_direction": "longitudinal"
        },
        {
          "name": "Crystal Rainbow Maple Leaf",
          "codes": [
            "HJ-PLA-CrystalRainbow-175MF1-US"
          ],
          "hexes": [
            "c0392b",
            "e74c3c",
            "f39c12",
            "d35400"
          ],
          "multi_color_direction": "longitudinal"
        },
        {
          "name": "Crystal Rainbow Nebulae",
          "codes": [
            "HJ-PLA-CrystalRainbow-175TBP1-US"
          ],
          "hexes": [
            "4b0082",
            "8e24aa",
            "3949ab",
            "e040fb"
          ],
          "multi_color_direction": "longitudinal"
        },
        {
          "name": "Crystal Rainbow Prairie",
          "codes": [
            "HJ-PLA-CrystalRainbow-175TBG1-US"
          ],
          "hexes": [
            "7cb342",
            "aed581",
            "fff176",
            "81c784"
          ],
          "multi_color_direction": "longitudinal"
        },
        {
          "name": "Crystal Rainbow Wheat Field",
          "codes": [
            "HJ-PLA-CrystalRainbow-175WF1-US"
          ],
          "hexes": [
            "f4d03f",
            "f9e79f",
            "f5b041",
            "d4ac0d"
          ],
          "multi_color_direction": "longitudinal"
        }
      ],
      "finish": "glossy",
      "multi_color_direction": "longitudinal"
    },
    {
      "name": "Matte PLA {color_name}",
      "material": "PLA",
      "density": 1.24,
      "weights": [
        {
          "weight": 1000,
          "spool_type": "plastic"
        }
      ],
      "diameters": [
        1.75
      ],
      "extruder_temp_range": [
        190,
        220
      ],
      "bed_temp_range": [
        50,
        60
      ],
      "country_of_origin": "China",
      "colors": [
        {
          "name": "Matte Almond Yellow",
          "codes": [
            "HJ-Matte PLA-175Y1KG-DE",
            "HJ-Matte PLA-175Y1KG-US"
          ],
          "hex": "efdecd"
        },
        {
          "name": "Matte Dark Grey",
          "codes": [
            "HJ-Matte PLA-175DH1KG-DE",
            "HJ-Matte PLA-175DH1KG-US"
          ],
          "hex": "4a4a4a"
        },
        {
          "name": "Matte Deep Black",
          "codes": [
            "HJ-Matte PLA-175DP1KG-DE",
            "HJ-Matte PLA-175DP1KG-US"
          ],
          "hex": "1a1a1a"
        },
        {
          "name": "Matte Light Blue",
          "codes": [
            "HJ-Matte PLA-175LU1KG-DE",
            "HJ-Matte PLA-175LU1KG-US"
          ],
          "hex": "87ceeb"
        },
        {
          "name": "Matte Light Khaki",
          "codes": [
            "HJ-Matte PLA-175LK1KG-DE",
            "HJ-Matte PLA-175LK1KG-US"
          ],
          "hex": "808080"
        },
        {
          "name": "Matte Milky White",
          "codes": [
            "HJ-Matte PLA-175NW1KG-DE",
            "HJ-Matte PLA-175NW1KG-US"
          ],
          "hex": "faf8f5"
        },
        {
          "name": "Matte Mint Green",
          "codes": [
            "HJ-Matte PLA-175MG1KG-DE",
            "HJ-Matte PLA-175MG1KG-US"
          ],
          "hex": "98ff98"
        },
        {
          "name": "Matte Morandi Purple",
          "codes": [
            "HJ-Matte PLA-175Z1KG-DE",
            "HJ-Matte PLA-175Z1KG-US"
          ],
          "hex": "9b8ec4"
        },
        {
          "name": "Matte Peach Pink",
          "codes": [
            "HJ-Matte PLA-175P1KG-DE",
            "HJ-Matte PLA-175P1KG-US"
          ],
          "hex": "ff69b4"
        },
        {
          "name": "Matte Tangerine",
          "codes": [
            "HJ-Matte PLA-175O1KG-DE",
            "HJ-Matte PLA-175O1KG-US"
          ],
          "hex": "808080"
        }
      ],
      "finish": "matte"
    },
    {
      "name": "PETG {color_name}",
      "material": "PETG",
      "density": 1.27,
      "weights": [
        {
          "weight": 1000,
          "spool_type": "plastic"
        }
      ],
      "diameters": [
        1.75
      ],
      "extruder_temp_range": [
        220,
        250
      ],
      "bed_temp_range": [
        70,
        80
      ],
      "country_of_origin": "China",
      "colors": [
        {
          "name": "PETG Blue",
          "codes": [
            "HJ-PETG-175SU1KG-US"
          ],
          "hex": "1e3a8a"
        },
        {
          "name": "PETG Green",
          "codes": [
            "HJ-PETG-175G1KG-US"
          ],
          "hex": "2e7d32"
        },
        {
          "name": "PETG Natural",
          "codes": [
            "HJ-PETG-175SN1KG-US"
          ],
          "hex": "d4c4a8"
        },
        {
          "name": "PETG Orange",
          "codes": [
            "HJ-PETG-175SO1KG-US"
          ],
          "hex": "ff8c00"
        },
        {
          "name": "PETG Solid Black",
          "codes": [
            "HJ-PETG-175SB1KG-US-001"
          ],
          "hex": "1a1a1a"
        },
        {
          "name": "PETG Solid Blue",
          "codes": [
            "HJ-PETG-175U1KG-US"
          ],
          "hex": "1e3a8a"
        },
        {
          "name": "PETG Solid Grey",
          "codes": [
            "HJ-PETG-175SH1KG-US-001"
          ],
          "hex": "808080"
        },
        {
          "name": "PETG Solid Red",
          "codes": [
            "HJ-PETG-175SR1KG-US"
          ],
          "hex": "c41e2a"
        },
        {
          "name": "PETG Solid Silver",
          "codes": [
            "HJ-PETG-175SS1KG-US"
          ],
          "hex": "c0c0c0"
        },
        {
          "name": "PETG Solid White",
          "codes": [
            "HJ-PETG-175SW1KG-US-001"
          ],
          "hex": "f5f5f5"
        }
      ]
    },
    {
      "name": "PLA Lite {color_name}",
      "material": "PLA",
      "density": 1.24,
      "weights": [
        {
          "weight": 1000,
          "spool_type": "plastic"
        }
      ],
      "diameters": [
        1.75
      ],
      "extruder_temp_range": [
        190,
        220
      ],
      "bed_temp_range": [
        50,
        60
      ],
      "country_of_origin": "China",
      "colors": [
        {
          "name": "PLA Blue",
          "codes": [
            "HJ-PLA Lite-175U1KG-US"
          ],
          "hex": "1e3a8a"
        },
        {
          "name": "PLA Fire Engine Red",
          "codes": [
            "HJ-PLA Lite-175FR1KG-US"
          ],
          "hex": "ce2029"
        },
        {
          "name": "PLA Green",
          "codes": [
            "HJ-PLA Lite-175G1KG-US"
          ],
          "hex": "2e7d32"
        },
        {
          "name": "PLA Lite Black",
          "codes": [
            "HJ-PLA Lite-175B1KG-US"
          ],
          "hex": "1a1a1a"
        },
        {
          "name": "PLA Lite Cold White",
          "codes": [
            "HJ-PLA Lite-175CW1KG-US"
          ],
          "hex": "f5f5f5"
        },
        {
          "name": "PLA Lite Grey",
          "codes": [
            "HJ-PLA Lite-175H1KG-US"
          ],
          "hex": "808080"
        },
        {
          "name": "PLA Red",
          "codes": [
            "HJ-PLA Lite-175R1KG-US"
          ],
          "hex": "c41e2a"
        },
        {
          "name": "PLA Very Peri",
          "codes": [
            "HJ-PLA Lite-175F1KG-US"
          ],
          "hex": "6667ab"
        },
        {
          "name": "PLA White",
          "codes": [
            "HJ-PLA Lite-175W1KG-US"
          ],
          "hex": "f5f5f5"
        },
        {
          "name": "PLA Yellow",
          "codes": [
            "HJ-PLA Lite-175Y1KG-US"
          ],
          "hex": "ffd700"
        }
      ]
    },
    {
      "name": "PLA Pro {color_name}",
      "material": "PLA+",
      "density": 1.24,
      "weights": [
        {
          "weight": 1000,
          "spool_type": "plastic"
        }
      ],
      "diameters": [
        1.75
      ],
      "extruder_temp_range": [
        200,
        230
      ],
      "bed_temp_range": [
        50,
        70
      ],
      "country_of_origin": "China",
      "colors": [
        {
          "name": "PLA Pro Beige",
          "codes": [
            "HJ-PLA Pro-175BG1-US"
          ],
          "hex": "d4b896"
        },
        {
          "name": "PLA Pro Black",
          "codes": [
            "HJ-PLA Pro-175B1KG -DE",
            "HJ-PLA Pro-175B1KG -US"
          ],
          "hex": "1a1a1a"
        },
        {
          "name": "PLA Pro Blue",
          "codes": [
            "HJ-PLA Pro-175U1KG -DE",
            "HJ-PLA Pro-175U1KG -US"
          ],
          "hex": "1e3a8a"
        },
        {
          "name": "PLA Pro Bone White",
          "codes": [
            "HJ-PLA Pro-175BW1"
          ],
          "hex": "f5f5f5"
        },
        {
          "name": "PLA Pro Brown",
          "codes": [
            "HJ-PLA Pro-175C1",
            "HJ-PLA Pro-175C1-DE"
          ],
          "hex": "8b4513"
        },
        {
          "name": "PLA Pro Cold White",
          "codes": [
            "HJ-PLA Pro-175W1KG -DE",
            "HJ-PLA Pro-175W1KG -US"
          ],
          "hex": "f5f5f5"
        },
        {
          "name": "PLA Pro Green",
          "codes": [
            "HJ-PLA Pro-175G1-US"
          ],
          "hex": "2e7d32"
        },
        {
          "name": "PLA Pro Grey",
          "codes": [
            "HJ-PLA Pro-175H1KG -DE",
            "HJ-PLA Pro-175H1KG -US"
          ],
          "hex": "808080"
        },
        {
          "name": "PLA Pro Light Blue",
          "codes": [
            "HJ-PLA Pro-175D1-US"
          ],
          "hex": "1e3a8a"
        },
        {
          "name": "PLA Pro Orange",
          "codes": [
            "HJ-PLA Pro-175O1-DE",
            "HJ-PLA Pro-175O1-US"
          ],
          "hex": "ff8c00"
        },
        {
          "name": "PLA Pro Peak Green",
          "codes": [
            "HJ-PLA Pro-175V1"
          ],
          "hex": "2e7d32"
        },
        {
          "name": "PLA Pro Pink",
          "codes": [
            "HJ-PLA Pro-175P1-DE",
            "HJ-PLA Pro-175P1-US"
          ],
          "hex": "ff69b4"
        },
        {
          "name": "PLA Pro Purple",
          "codes": [
            "HJ-PLA Pro-175Z1-US"
          ],
          "hex": "800080"
        },
        {
          "name": "PLA Pro Red",
          "codes": [
            "HJ-PLA Pro-175R1KG -DE",
            "HJ-PLA Pro-175R1KG -US"
          ],
          "hex": "c41e2a"
        },
        {
          "name": "PLA Pro Silver",
          "codes": [
            "HJ-PLA Pro-175S1-US",
            "HJ-PLA Pro-175S1KG -US"
          ],
          "hex": "c0c0c0"
        },
        {
          "name": "PLA Pro Yellow",
          "codes": [
            "HJ-PLA Pro-175Y1-DE",
            "HJ-PLA Pro-175Y1-US"
          ],
          "hex": "ffd700"
        }
      ]
    },
    {
      "name": "Rapid PLA {color_name}",
      "material": "PLA",
      "density": 1.24,
      "weights": [
        {
          "weight": 1000,
          "spool_type": "plastic"
        }
      ],
      "diameters": [
        1.75
      ],
      "extruder_temp_range": [
        190,
        220
      ],
      "bed_temp_range": [
        50,
        60
      ],
      "country_of_origin": "China",
      "colors": [
        {
          "name": "Rapid Black",
          "codes": [
            "HJ-PLA HS-175B1KG-US"
          ],
          "hex": "1a1a1a"
        },
        {
          "name": "Rapid Blue",
          "codes": [
            "HJ-PLA HS-175U1KG-US"
          ],
          "hex": "1e3a8a"
        },
        {
          "name": "Rapid Grey",
          "codes": [
            "HJ-PLA HS-175H1KG-US"
          ],
          "hex": "808080"
        },
        {
          "name": "Rapid Orange",
          "codes": [
            "HJ-PLA HS-175O1KG-US"
          ],
          "hex": "ff8c00"
        },
        {
          "name": "Rapid Red",
          "codes": [
            "HJ-PLA HS-175R1KG-US"
          ],
          "hex": "c41e2a"
        },
        {
          "name": "Rapid White",
          "codes": [
            "HJ-PLA HS-175W1KG-US"
          ],
          "hex": "f5f5f5"
        },
        {
          "name": "Rapid Yellow",
          "codes": [
            "HJ-PLA HS-175Y1KG-US"
          ],
          "hex": "ffd700"
        }
      ]
    },
    {
      "name": "Silk Magic Dual {color_name}",
      "material": "PLA",
      "density": 1.24,
      "weights": [
        {
          "weight": 1000,
          "spool_type": "plastic"
        }
      ],
      "diameters": [
        1.75
      ],
      "extruder_temp_range": [
        190,
        220
      ],
      "bed_temp_range": [
        50,
        60
      ],
      "country_of_origin": "China",
      "colors": [
        {
          "name": "Black & Gold",
          "codes": [
            "HJ-PLA-SilkMagic-175BG1-US"
          ],
          "hexes": [
            "1a1a1a",
            "ffd700"
          ],
          "multi_color_direction": "coaxial"
        },
        {
          "name": "Black & Green",
          "codes": [
            "HJ-PLA-SilkMagic-175BE1-US"
          ],
          "hexes": [
            "1a1a1a",
            "2e7d32"
          ],
          "multi_color_direction": "coaxial"
        },
        {
          "name": "Black & Purple",
          "codes": [
            "HJ-PLA-SilkMagic-175BP1-US"
          ],
          "hexes": [
            "1a1a1a",
            "800080"
          ],
          "multi_color_direction": "coaxial"
        },
        {
          "name": "Black & Red",
          "codes": [
            "HJ-PLA-SilkMagic-175BR1-US"
          ],
          "hexes": [
            "1a1a1a",
            "c41e2a"
          ],
          "multi_color_direction": "coaxial"
        },
        {
          "name": "Blue & Green",
          "codes": [
            "HJ-PLA-SilkMagic-175LG1-US"
          ],
          "hexes": [
            "1e3a8a",
            "2e7d32"
          ],
          "multi_color_direction": "coaxial"
        },
        {
          "name": "Blue & Purple",
          "codes": [
            "HJ-PLA-SilkMagic-175LP1-US"
          ],
          "hexes": [
            "1e3a8a",
            "800080"
          ],
          "multi_color_direction": "coaxial"
        },
        {
          "name": "Blue & Silver",
          "codes": [
            "HJ-PLA-SilkMagic-175LS1-US"
          ],
          "hexes": [
            "1e3a8a",
            "c0c0c0"
          ],
          "multi_color_direction": "coaxial"
        },
        {
          "name": "Gold & Silver",
          "codes": [
            "HJ-PLA-SilkMagic-175GS1-US"
          ],
          "hexes": [
            "ffd700",
            "c0c0c0"
          ],
          "multi_color_direction": "coaxial"
        },
        {
          "name": "Purple & Gold",
          "codes": [
            "HJ-PLA-SilkMagic-175PD1-US"
          ],
          "hexes": [
            "800080",
            "ffd700"
          ],
          "multi_color_direction": "coaxial"
        },
        {
          "name": "Purple & Green",
          "codes": [
            "HJ-PLA-SilkMagic-175PG1-US"
          ],
          "hexes": [
            "800080",
            "2e7d32"
          ],
          "multi_color_direction": "coaxial"
        },
        {
          "name": "Red & Blue",
          "codes": [
            "HJ-PLA-SilkMagic-175RL1-US"
          ],
          "hexes": [
            "c41e2a",
            "1e3a8a"
          ],
          "multi_color_direction": "coaxial"
        },
        {
          "name": "Red & Gold",
          "codes": [
            "HJ-PLA-SilkMagic-175RG1-US"
          ],
          "hexes": [
            "c41e2a",
            "ffd700"
          ],
          "multi_color_direction": "coaxial"
        },
        {
          "name": "Red & Green",
          "codes": [
            "HJ-PLA-SilkMagic-175RE1-US"
          ],
          "hexes": [
            "c41e2a",
            "2e7d32"
          ],
          "multi_color_direction": "coaxial"
        }
      ],
      "finish": "glossy",
      "multi_color_direction": "coaxial"
    },
    {
      "name": "Silk Mystic Tri {color_name}",
      "material": "PLA",
      "density": 1.24,
      "weights": [
        {
          "weight": 1000,
          "spool_type": "plastic"
        }
      ],
      "diameters": [
        1.75
      ],
      "extruder_temp_range": [
        190,
        220
      ],
      "bed_temp_range": [
        50,
        60
      ],
      "country_of_origin": "China",
      "colors": [
        {
          "name": "Black-Red-Gold",
          "codes": [
            "HJ-PLA-SilkMystic-175BRG1-US"
          ],
          "hexes": [
            "1a1a1a",
            "c41e2a",
            "ffd700"
          ],
          "multi_color_direction": "coaxial"
        },
        {
          "name": "Blue-Green-Orange",
          "codes": [
            "HJ-PLA-SilkMystic-175LOG1-US"
          ],
          "hexes": [
            "1e3a8a",
            "2e7d32",
            "ff8c00"
          ],
          "multi_color_direction": "coaxial"
        },
        {
          "name": "Blue-Purple-Red",
          "codes": [
            "HJ-PLA-SilkMystic-175LPR1-US"
          ],
          "hexes": [
            "1e3a8a",
            "800080",
            "c41e2a"
          ],
          "multi_color_direction": "coaxial"
        },
        {
          "name": "Gold-Silver-Copper",
          "codes": [
            "HJ-PLA-SilkMystic-175GSO1-US"
          ],
          "hexes": [
            "ffd700",
            "c0c0c0",
            "b87333"
          ],
          "multi_color_direction": "coaxial"
        },
        {
          "name": "Red-Gold-Purple",
          "codes": [
            "HJ-PLA-SilkMystic-175RGP1-US"
          ],
          "hexes": [
            "c41e2a",
            "ffd700",
            "800080"
          ],
          "multi_color_direction": "coaxial"
        },
        {
          "name": "Red-Green-Blue",
          "codes": [
            "HJ-PLA-SilkMystic-175RGL1-US"
          ],
          "hexes": [
            "c41e2a",
            "2e7d32",
            "1e3a8a"
          ],
          "multi_color_direction": "coaxial"
        },
        {
          "name": "Red-Yellow-Blue",
          "codes": [
            "HJ-PLA-SilkMystic-175RYB1-US"
          ],
          "hexes": [
            "c41e2a",
            "ffd700",
            "1e3a8a"
          ],
          "multi_color_direction": "coaxial"
        }
      ],
      "finish": "glossy",
      "multi_color_direction": "coaxial"
    },
    {
      "name": "Silk PLA {color_name}",
      "material": "PLA",
      "density": 1.24,
      "weights": [
        {
          "weight": 1000,
          "spool_type": "plastic"
        }
      ],
      "diameters": [
        1.75
      ],
      "extruder_temp_range": [
        190,
        220
      ],
      "bed_temp_range": [
        50,
        60
      ],
      "country_of_origin": "China",
      "colors": [
        {
          "name": "Silk Blue",
          "codes": [
            "HJ-Silk PLA-175U1-DE",
            "HJ-Silk PLA-175U1-US"
          ],
          "hex": "1e3a8a"
        },
        {
          "name": "Silk Bronze",
          "codes": [
            "HJ-Silk PLA-175BR1-DE",
            "HJ-Silk PLA-175BR1-US"
          ],
          "hex": "cd7f32"
        },
        {
          "name": "Silk Copper",
          "codes": [
            "HJ-Silk PLA-175CO1KG-DE-001",
            "HJ-Silk PLA-175CO1KG-US-001"
          ],
          "hex": "b87333"
        },
        {
          "name": "Silk Gold",
          "codes": [
            "HJ-Silk PLA-175J1KG-US-001"
          ],
          "hex": "ffd700"
        },
        {
          "name": "Silk Green",
          "codes": [
            "HJ-Silk PLA-175G1-DE",
            "HJ-Silk PLA-175G1-US"
          ],
          "hex": "2e7d32"
        },
        {
          "name": "Silk Pink",
          "codes": [
            "HJ-Silk PLA-175P1-US"
          ],
          "hex": "ff69b4"
        },
        {
          "name": "Silk Purple",
          "codes": [
            "HJ-Silk PLA-175Z1-US"
          ],
          "hex": "800080"
        },
        {
          "name": "Silk Red",
          "codes": [
            "HJ-Silk PLA-175R1-US"
          ],
          "hex": "c41e2a"
        },
        {
          "name": "Silk Silver",
          "codes": [
            "HJ-Silk PLA-175S1KG-DE-001",
            "HJ-Silk PLA-175S1KG-US-001"
          ],
          "hex": "c0c0c0"
        },
        {
          "name": "Silk White",
          "codes": [
            "HJ-Silk PLA-175W1-US"
          ],
          "hex": "f5f5f5"
        }
      ],
      "finish": "glossy"
    },
    {
      "name": "Silk Rainbow PLA {color_name}",
      "material": "PLA",
      "density": 1.24,
      "weights": [
        {
          "weight": 1000,
          "spool_type": "plastic"
        }
      ],
      "diameters": [
        1.75
      ],
      "extruder_temp_range": [
        190,
        220
      ],
      "bed_temp_range": [
        50,
        60
      ],
      "country_of_origin": "China",
      "colors": [
        {
          "name": "Silk Rainbow Blood Orange",
          "codes": [
            "HJ-PLA-SilkRainbow-175BN1-US"
          ],
          "hexes": [
            "ff4500",
            "ff6347",
            "ff8c00",
            "dc143c"
          ],
          "multi_color_direction": "longitudinal"
        },
        {
          "name": "Silk Rainbow Coral Reef",
          "codes": [
            "HJ-PLA-SilkRainbow-175CF1-US"
          ],
          "hexes": [
            "ff7f50",
            "ff6347",
            "ffa07a",
            "20b2aa"
          ],
          "multi_color_direction": "longitudinal"
        },
        {
          "name": "Silk Rainbow Fiery Rose",
          "codes": [
            "HJ-PLA-SilkRainbow-175LS1-US"
          ],
          "hexes": [
            "ff0000",
            "ff8800",
            "ffff00",
            "00ff00",
            "0000ff",
            "8b00ff"
          ],
          "multi_color_direction": "longitudinal"
        },
        {
          "name": "Silk Rainbow Ivy",
          "codes": [
            "HJ-PLA-SilkRainbow-175IV1-US"
          ],
          "hexes": [
            "228b22",
            "32cd32",
            "90ee90",
            "006400"
          ],
          "multi_color_direction": "longitudinal"
        },
        {
          "name": "Silk Rainbow Lavender",
          "codes": [
            "HJ-PLA-SilkRainbow-175LD1-US"
          ],
          "hexes": [
            "e6e6fa",
            "d8bfd8",
            "b19cd9",
            "9370db"
          ],
          "multi_color_direction": "longitudinal"
        },
        {
          "name": "Silk Rainbow Macaron",
          "codes": [
            "HJ-PLA-SilkRainbow-175RBA1-US"
          ],
          "hexes": [
            "ffb7c5",
            "b5ead7",
            "c7ceea",
            "ffdac1"
          ],
          "multi_color_direction": "longitudinal"
        },
        {
          "name": "Silk Rainbow Tulipa",
          "codes": [
            "HJ-PLA-SilkRainbow-175TU1-US"
          ],
          "hexes": [
            "ff6b8a",
            "ff1493",
            "ff69b4",
            "db7093"
          ],
          "multi_color_direction": "longitudinal"
        }
      ],
      "finish": "glossy",
      "multi_color_direction": "longitudinal"
    },
    {
      "name": "TPU 95A {color_name}",
      "material": "TPU",
      "density": 1.21,
      "weights": [
        {
          "weight": 1000,
          "spool_type": "plastic"
        }
      ],
      "diameters": [
        1.75
      ],
      "extruder_temp_range": [
        200,
        230
      ],
      "bed_temp_range": [
        40,
        60
      ],
      "country_of_origin": "China",
      "colors": [
        {
          "name": "Black",
          "codes": [
            "HJ-TPU-95A175B1"
          ],
          "hex": "1a1a1a"
        },
        {
          "name": "Clear",
          "codes": [
            "HJ-TPU-95A175N1"
          ],
          "hex": "ffffff",
          "translucent": true
        },
        {
          "name": "Grey",
          "codes": [
            "HJ-TPU-95A175H1"
          ],
          "hex": "808080"
        },
        {
          "name": "Transparent Blue",
          "codes": [
            "HJ-TPU-95A175GU1"
          ],
          "hex": "6eb5ff",
          "translucent": true
        },
        {
          "name": "Transparent Red",
          "codes": [
            "HJ-TPU-95A175GR1"
          ],
          "hex": "ff6b6b",
          "translucent": true
        },
        {
          "name": "White",
          "codes": [
            "HJ-TPU-95A175W1"
          ],
          "hex": "f5f5f5"
        }
      ]
    },
    {
      "name": "Wood PLA {color_name}",
      "material": "PLA",
      "density": 1.24,
      "weights": [
        {
          "weight": 1000,
          "spool_type": "plastic"
        }
      ],
      "diameters": [
        1.75
      ],
      "extruder_temp_range": [
        190,
        220
      ],
      "bed_temp_range": [
        50,
        60
      ],
      "country_of_origin": "China",
      "colors": [
        {
          "name": "Wood PLA Natural",
          "codes": [
            "HJ-Wood PLA-175N1"
          ],
          "hex": "c4a574"
        }
      ],
      "fill": "wood"
    }
  ]
}